hn_data_fetcher/__init__.py
hn_data_fetcher/delete_from_tigris.py
hn_data_fetcher/hn_data_fetcher.py
hn_data_fetcher/hn_to_hive.py
hn_data_fetcher/upload_to_tigris.py
hn_data_fetcher-1.2.1.dist-info/METADATA
hn_data_fetcher-1.2.1.dist-info/WHEEL
hn_data_fetcher-1.2.1.dist-info/entry_points.txt
hn_data_fetcher-1.2.1.dist-info/RECORD
