Metadata-Version: 2.4
Name: hn-data-fetcher
Version: 1.2.1
Summary: A high-performance asynchronous tool for fetching and storing Hacker News items in a SQLite database.
Project-URL: Homepage, https://github.com/adhikasp/hn-data-fetcher
Project-URL: Bug Tracker, https://github.com/adhikasp/hn-data-fetcher/issues
Author-email: Adhika Setya Pramudita <adhika.setya.p@gmail.com>
Classifier: License :: OSI Approved :: MIT License
Classifier: Operating System :: OS Independent
Classifier: Programming Language :: Python :: 3
Requires-Python: >=3.8
Requires-Dist: boto3>=1.26.0
Requires-Dist: pandas>=1.3.0
Requires-Dist: pyarrow>=7.0.0
Requires-Dist: python-dotenv>=1.0.0
Requires-Dist: rich>=13.0.0
Requires-Dist: sqlalchemy>=1.4.0
Provides-Extra: dev
Requires-Dist: black>=23.3.0; extra == 'dev'
Requires-Dist: mypy>=1.3.0; extra == 'dev'
Requires-Dist: pytest-cov>=4.0.0; extra == 'dev'
Requires-Dist: pytest-mock>=3.10.0; extra == 'dev'
Requires-Dist: pytest>=7.0.0; extra == 'dev'
Requires-Dist: ruff>=0.0.270; extra == 'dev'
